cruiz/RELEASE_VERSION.py
cruiz/__init__.py
cruiz/__main__.py
cruiz/application.py
cruiz/config.py
cruiz/constants.py
cruiz/dumpobjecttypes.py
cruiz/entrypoint.py
cruiz/environ.py
cruiz/exceptions.py
cruiz/globals.py
cruiz/mainwindow.py
cruiz/resourcegeneration.py
cruiz/restart.py
cruiz/revealonfilesystem.py
cruiz/runcommands.py
cruiz/svggraph.py
cruiz/version.py
cruiz/commands/__init__.py
cruiz/commands/conanconf.py
cruiz/commands/conanenv.py
cruiz/commands/conaninvocation.py
cruiz/commands/context.py
cruiz/commands/guardedlisttoflush.py
cruiz/commands/logdetails.py
cruiz/commands/messagereplyprocessor.py
cruiz/commands/metarequestconaninvocation.py
cruiz/interop/__init__.py
cruiz/interop/commandparameters.py
cruiz/interop/commonparameters.py
cruiz/interop/dependencygraph.py
cruiz/interop/message.py
cruiz/interop/packagebinaryparameters.py
cruiz/interop/packageidparameters.py
cruiz/interop/packagenode.py
cruiz/interop/packagerevisionsparameters.py
cruiz/interop/pod.py
cruiz/interop/reciperevisionsparameters.py
cruiz/interop/searchrecipesparameters.py
cruiz/load_recipe/__init__.py
cruiz/load_recipe/loadrecipewizard.py
cruiz/load_recipe/pages/__init__.py
cruiz/load_recipe/pages/initialprofilepage.py
cruiz/load_recipe/pages/intropage.py
cruiz/load_recipe/pages/localcachepage.py
cruiz/load_recipe/pages/packageversionpage.py
cruiz/manage_local_cache/__init__.py
cruiz/manage_local_cache/managelocalcachesdialog.py
cruiz/manage_local_cache/widgets/__init__.py
cruiz/manage_local_cache/widgets/addenvironmentdialog.py
cruiz/manage_local_cache/widgets/addextraprofiledirectorydialog.py
cruiz/manage_local_cache/widgets/addremotedialog.py
cruiz/manage_local_cache/widgets/configpathorurl.py
cruiz/manage_local_cache/widgets/installconfigdialog.py
cruiz/manage_local_cache/widgets/keyvaluetable.py
cruiz/manage_local_cache/widgets/movelocalcachedialog.py
cruiz/manage_local_cache/widgets/newlocalcachewizard.py
cruiz/manage_local_cache/widgets/newlocalcachewizardpages.py
cruiz-1.4.1.dist-info/LICENSE
cruiz-1.4.1.dist-info/METADATA
cruiz-1.4.1.dist-info/NOTICE
cruiz-1.4.1.dist-info/WHEEL
cruiz-1.4.1.dist-info/entry_points.txt
cruiz-1.4.1.dist-info/top_level.txt
cruiz-1.4.1.dist-info/RECORD
