Metadata-Version: 2.1
Name: cruiz
Version: 1.4.1
Summary: Conan recipe user interface
Home-page: https://github.com/markfinal/cruiz
Author: Mark Final
Author-email: markfinal@hotmail.com
Project-URL: Documentation, https://cruiz.readthedocs.io/en/latest/
Project-URL: GitHub, https://github.com/markfinal/cruiz
Classifier: Development Status :: 5 - Production/Stable
Classifier: Intended Audience :: Developers
Classifier: Topic :: Software Development :: Build Tools
Classifier: License :: OSI Approved :: Apache Software License
Classifier: Programming Language :: Python :: 3.9
Classifier: Programming Language :: Python :: 3.10
Classifier: Programming Language :: Python :: 3.11
Classifier: Programming Language :: Python :: 3.12
Classifier: Programming Language :: Python :: 3.13
Requires-Python: >=3.9, <3.14
License-File: LICENSE
License-File: NOTICE
Requires-Dist: PySide6<6.9,>=6.8
Requires-Dist: qtpy<2.5,>=2.4.2
Requires-Dist: conan<3
Requires-Dist: graphviz<1,>=0.19.1
Requires-Dist: psutil<6,>=5.9.0
Requires-Dist: GitPython<4,>=3.1.26
Requires-Dist: validators<1,>=0.18.2
